cortexannotate/__init__.py
cortexannotate/_config.py
cortexannotate/_control.py
cortexannotate/_core.py
cortexannotate/_figure.py
cortexannotate/_util.py
cortexannotate/prfs.py
cortexannotate-0.1.4.dist-info/LICENSE
cortexannotate-0.1.4.dist-info/METADATA
cortexannotate-0.1.4.dist-info/WHEEL
cortexannotate-0.1.4.dist-info/top_level.txt
cortexannotate-0.1.4.dist-info/RECORD
